LICENSE
README.md
xpath/__init__.py
xpath_expressions-1.0.2.dist-info/LICENSE
xpath_expressions-1.0.2.dist-info/WHEEL
xpath_expressions-1.0.2.dist-info/METADATA
xpath_expressions-1.0.2.dist-info/RECORD
