Metadata-Version: 2.1
Name: xpath-expressions
Version: 1.0.2
Summary: Treat XPath expressions as Python objects 
Home-page: https://github.com/orf/xpath-expressions
License: MIT
Author: orf
Author-email: tom@tomforb.es
Requires-Python: >3.5
Classifier: License :: OSI Approved :: MIT License
Classifier: Programming Language :: Python :: 3
Classifier: Programming Language :: Python :: 3.6
Classifier: Programming Language :: Python :: 3.7
Classifier: Programming Language :: Python :: 3.8
